nanalysis/__init__.py
nanalysis/find_roots.py
nanalysis/interpolation.py
nanalysis/lin_systems.py
nanalysis/num_methods.py
nanalysis-1.41.dist-info/METADATA
nanalysis-1.41.dist-info/WHEEL
nanalysis-1.41.dist-info/top_level.txt
nanalysis-1.41.dist-info/RECORD
