Metadata-Version: 2.1
Name: nanalysis
Version: 1.41
Summary: UNKNOWN
Home-page: https://github.com/mwstrand/numerical-analysis
Author: Michael Strand
Author-email: mwstrand@uci.edu
License: UNKNOWN
Platform: UNKNOWN
Requires-Dist: numpy
